extras/__init__.py
extras/divide.py
extras/multiply.py
verysimplemodulex-0.0.1.dist-info/METADATA
verysimplemodulex-0.0.1.dist-info/WHEEL
verysimplemodulex-0.0.1.dist-info/top_level.txt
verysimplemodulex-0.0.1.dist-info/RECORD
